mediaflowvideo/__init__.py
mediaflowvideo/admin.py
mediaflowvideo/apps.py
mediaflowvideo/draftail.py
mediaflowvideo/models.py
mediaflowvideo/tests.py
mediaflowvideo/views.py
mediaflowvideo/wagtail_hooks.py
mediaflowvideo/locale/sv/LC_MESSAGES
mediaflowvideo/migrations/__init__.py
mediaflowvideo/static/css/draftail-videoentity.css
mediaflowvideo/static/js/draftail-videoentity.js
mediaflowvideo/static/js/mediaflowvideoblock-telepath.js
mediaflowvideo/static/js/mf-embed-js.js
mediaflowvideo/templates/mediaflowvideo/mediaflow-video-block.html
mediaflowvideo/templates/mediaflowvideo/mediaflow-video-form.html
mediaflowvideo/templates/mediaflowvideo/mediaflow-video-modal.html
mediaflowvideo-1.0.2.dist-info/METADATA
mediaflowvideo-1.0.2.dist-info/WHEEL
mediaflowvideo-1.0.2.dist-info/licenses/LICENSE
mediaflowvideo-1.0.2.dist-info/RECORD
