Metadata-Version: 2.4
Name: mediaflowvideo
Version: 1.0.2
Summary: Wagtail video plugin for Mediaflow
Project-URL: Homepage, https://support.mediaflow.com
Project-URL: Issues, https://support.mediaflow.com
Author-email: Mediaflow Europe AB <support@mediaflow.com>
License-File: LICENSE
Classifier: License :: OSI Approved :: MIT License
Classifier: Operating System :: OS Independent
Classifier: Programming Language :: Python :: 3
Requires-Python: >=3.8
